CHANGES.rst
LICENSE
MANIFEST.in
README.rst
setup.cfg
setup.py
kinesis_producer/__init__.py
kinesis_producer/accumulator.py
kinesis_producer/buffer.py
kinesis_producer/client.py
kinesis_producer/constants.py
kinesis_producer/partitioner.py
kinesis_producer/producer.py
kinesis_producer/sender.py
kinesis_producer.egg-info/PKG-INFO
kinesis_producer.egg-info/SOURCES.txt
kinesis_producer.egg-info/dependency_links.txt
kinesis_producer.egg-info/not-zip-safe
kinesis_producer.egg-info/requires.txt
kinesis_producer.egg-info/top_level.txt