Metadata-Version: 1.1
Name: kinesis-producer
Version: 0.2.1
Summary: Producer for AWS Kinesis Stream with record aggregation
Home-page: https://github.com/ludia/kinesis_producer
Author: Pior Bastida
Author-email: pbastida@ludia.com
License: MIT
Keywords: kinesis kafka producer client
Platform: UNKNOWN
Classifier: Development Status :: 3 - Alpha
Classifier: Intended Audience :: Developers
Classifier: License :: OSI Approved :: MIT License
Classifier: Operating System :: OS Independent
Classifier: Topic :: Internet
Classifier: Programming Language :: Python :: 2.7
Classifier: Programming Language :: Python :: 3.3
Classifier: Programming Language :: Python :: 3.4
Classifier: Programming Language :: Python :: 3.5
Classifier: Programming Language :: Python :: Implementation :: PyPy
